ess/amor/__init__.py
ess/amor/conversions.py
ess/amor/data.py
ess/amor/geometry.py
ess/amor/instrument_view.py
ess/amor/load.py
ess/amor/normalization.py
ess/amor/orso.py
ess/amor/resolution.py
ess/amor/types.py
ess/amor/utils.py
ess/amor/workflow.py
ess/estia/__init__.py
ess/estia/beamline.py
ess/estia/calibration.py
ess/estia/conversions.py
ess/estia/corrections.py
ess/estia/data.py
ess/estia/load.py
ess/estia/maskings.py
ess/estia/mcstas.py
ess/estia/normalization.py
ess/estia/orso.py
ess/estia/resolution.py
ess/estia/types.py
ess/estia/workflow.py
ess/offspec/__init__.py
ess/offspec/conversions.py
ess/offspec/corrections.py
ess/offspec/data.py
ess/offspec/load.py
ess/offspec/maskings.py
ess/offspec/normalization.py
ess/offspec/types.py
ess/offspec/workflow.py
ess/reflectometry/__init__.py
ess/reflectometry/conversions.py
ess/reflectometry/corrections.py
ess/reflectometry/figures.py
ess/reflectometry/gui.py
ess/reflectometry/load.py
ess/reflectometry/normalization.py
ess/reflectometry/orso.py
ess/reflectometry/py.typed
ess/reflectometry/tools.py
ess/reflectometry/types.py
ess/reflectometry/workflow.py
ess/reflectometry/supermirror/__init__.py
ess/reflectometry/supermirror/types.py
essreflectometry-25.12.0.dist-info/licenses/LICENSE
essreflectometry-25.12.0.dist-info/METADATA
essreflectometry-25.12.0.dist-info/WHEEL
essreflectometry-25.12.0.dist-info/top_level.txt
essreflectometry-25.12.0.dist-info/RECORD
