Metadata-Version: 2.4
Name: essreflectometry
Version: 25.12.0
Summary: Reflectometry data reduction for the European Spallation Source
Author: Scipp contributors
License-Expression: BSD-3-Clause
Project-URL: Bug Tracker, https://github.com/scipp/essreflectometry/issues
Project-URL: Documentation, https://scipp.github.io/essreflectometry
Project-URL: Source, https://github.com/scipp/essreflectometry
Classifier: Intended Audience :: Science/Research
Classifier: Natural Language :: English
Classifier: Operating System :: OS Independent
Classifier: Programming Language :: Python :: 3
Classifier: Programming Language :: Python :: 3 :: Only
Classifier: Programming Language :: Python :: 3.11
Classifier: Programming Language :: Python :: 3.12
Classifier: Programming Language :: Python :: 3.13
Classifier: Topic :: Scientific/Engineering
Classifier: Typing :: Typed
Requires-Python: >=3.11
License-File: LICENSE
Requires-Dist: dask>=2022.1.0
Requires-Dist: python-dateutil
Requires-Dist: graphviz
Requires-Dist: plopp>=24.7.0
Requires-Dist: orsopy>=1.2
Requires-Dist: sciline>=24.6.0
Requires-Dist: scipp>=24.09.1
Requires-Dist: scippneutron>=24.10.0
Requires-Dist: scippnexus>=24.9.1
Requires-Dist: essreduce>=25.11.0
Requires-Dist: esspolarization>=25.7.0
Requires-Dist: essreduce>=25.4.0
Requires-Dist: pandas>=2.1.2
Provides-Extra: test
Requires-Dist: pytest>=7.0; extra == "test"
Requires-Dist: pooch>=1.5; extra == "test"
Provides-Extra: all
Requires-Dist: ipywidgets; extra == "all"
Requires-Dist: ipydatagrid; extra == "all"
Requires-Dist: ipytree; extra == "all"
Requires-Dist: pythreejs; extra == "all"
Dynamic: license-file
